which_key/__init__.py
which_key/cli.py
which_key/config.py
which_key/popup.py
which_key-0.2.2.dist-info/entry_points.txt
which_key-0.2.2.dist-info/LICENSE
which_key-0.2.2.dist-info/WHEEL
which_key-0.2.2.dist-info/METADATA
which_key-0.2.2.dist-info/RECORD
