Metadata-Version: 2.1
Name: which-key
Version: 0.2.2
Summary: Universal command launcher
Home-page: https://bsamseth.github.io/which-key/
License: MIT
Author: Bendik Samseth
Author-email: b.samseth@gmail.com
Requires-Python: >=3.9,<4.0
Classifier: License :: OSI Approved :: MIT License
Classifier: Programming Language :: Python :: 3
Classifier: Programming Language :: Python :: 3.10
Classifier: Programming Language :: Python :: 3.9
Requires-Dist: pydantic (>=1.8.2,<2.0.0)
Requires-Dist: toml (>=0.10.2,<0.11.0)
Requires-Dist: typer (>=0.4.0,<0.5.0)
Project-URL: Documentation, https://bsamseth.github.io/which-key/
Project-URL: Repository, https://github.com/bsamseth/which-key
